pygitlinguist/LICENSE
pygitlinguist/__init__.py
pygitlinguist/lang_detect.py
pygitlinguist/pylinguist.py
pygitlinguist/linguist/FileBlob.py
pygitlinguist/linguist/__init__.py
pygitlinguist/linguist/blob.py
pygitlinguist/linguist/blob_helper.py
pygitlinguist/linguist/classifier.py
pygitlinguist/linguist/documentation.yml
pygitlinguist/linguist/file_blob.py
pygitlinguist/linguist/generated.py
pygitlinguist/linguist/generic.yml
pygitlinguist/linguist/grammars.py
pygitlinguist/linguist/heuristics.py
pygitlinguist/linguist/heuristics.yml
pygitlinguist/linguist/language.py
pygitlinguist/linguist/languages.yml
pygitlinguist/linguist/lazy_blob.py
pygitlinguist/linguist/popular.yml
pygitlinguist/linguist/repository.py
pygitlinguist/linguist/samples.py
pygitlinguist/linguist/sha256.py
pygitlinguist/linguist/shebang.py
pygitlinguist/linguist/tokenizer.py
pygitlinguist/linguist/vendor.yml
pygitlinguist/linguist/version.py
pygitlinguist/linguist/strategy/__init__.py
pygitlinguist/linguist/strategy/extension.py
pygitlinguist/linguist/strategy/filename.py
pygitlinguist/linguist/strategy/manpage.py
pygitlinguist/linguist/strategy/modeline.py
pygitlinguist/linguist/strategy/xml.py
PyGitLinguist-1.5.1.dist-info/METADATA
PyGitLinguist-1.5.1.dist-info/WHEEL
PyGitLinguist-1.5.1.dist-info/top_level.txt
PyGitLinguist-1.5.1.dist-info/RECORD
